{
  "generated_at": "2026-06-28",
  "repository": "CherryHQ/cherry-studio",
  "methodology": "300-issue sample from 968 total open issues, ordered by updatedAt DESC. Health classification based on updatedAt recency.",

  "summary": {
    "total_open": 968,
    "active": {
      "count_estimated": 173,
      "pct": "~18%",
      "definition": "updatedAt within last 7 days",
      "note": "pages 1+2 of updatedAt-sorted list"
    },
    "aging": {
      "count_estimated": 127,
      "pct": "~13%",
      "definition": "updatedAt 7–30 days ago",
      "note": "late page 2 + page 3"
    },
    "stale": {
      "count_estimated": 300,
      "pct": "~31%",
      "definition": "updatedAt 30–90 days ago",
      "note": "estimated from pages 4–7 (not fully sampled)"
    },
    "zombie": {
      "count_estimated": 368,
      "pct": "~38%",
      "definition": "updatedAt >90 days ago",
      "note": "estimated from pages 7+ (not fully sampled)"
    }
  },

  "triage_backlog": {
    "needs_triage": 5,
    "needs_repro": 25,
    "needs_more_info": 6,
    "inactive_still_open": 102,
    "total_action_required": 138
  },

  "critical_items": [
    {
      "number": 15316,
      "title": "agents.db backup races with concurrent writes — corrupted restores",
      "severity": "DATA INTEGRITY",
      "category": "Bug",
      "milestone": "v1.9.8",
      "assignee": "kangfenmao",
      "status": "open / in progress",
      "impact": "Users syncing via Nutstore/WebDAV backup lose agents/sessions silently",
      "age_days": 34,
      "labels": ["needs-triage", "Data"]
    },
    {
      "number": 15409,
      "title": "CherryIN OAuth flow can be completed by a different renderer sender",
      "severity": "SECURITY",
      "category": "Bug",
      "status": "open (FIX SHIPPED in v1.9.11 via PR #15410)",
      "fix_pr": 15410,
      "fix_version": "v1.9.11",
      "note": "Issue remains open despite being fixed — should be closed",
      "labels": ["needs-triage", "inactive"]
    },
    {
      "number": 15826,
      "title": "@cherrystudio/ai-core CJS/type exports point to missing dist files",
      "severity": "ECOSYSTEM",
      "category": "Bug",
      "status": "open / needs triage",
      "impact": "CommonJS consumers and TypeScript declaration resolution broken for published package",
      "labels": ["needs-triage"]
    },
    {
      "number": 15983,
      "title": "MCP/Skill references in Agent SOUL.md lack automatic validation after deletion",
      "severity": "UX / AGENT RELIABILITY",
      "category": "Bug",
      "status": "open / needs triage",
      "labels": ["MCP", "needs-triage"]
    }
  ],

  "active_p1_issues": [
    {
      "number": 14899,
      "title": "[Feature]: Unified Notification Center",
      "labels": ["Planned", "P1", "feature", "UI/UX"],
      "status": "planned"
    },
    {
      "number": 13608,
      "title": "[Bug]: xiaomi mimo response only displays the last line",
      "labels": ["P1", "Models"],
      "status": "open — no assignee"
    },
    {
      "number": 13193,
      "title": "[Bug]: [AI_APICallError: Resource not found, default use responses API]",
      "labels": ["P1", "Models"],
      "assignee": "DeJeune",
      "status": "open — assigned"
    }
  ],

  "label_health_signals": {
    "inactive_open": 102,
    "blocked_v2_open": 2,
    "prd_issues": 14,
    "internal_team_issues": 46,
    "no_label_issues": 99
  },

  "unlabeled_ratio": "10.2%",
  "internal_driven_pct": "~15% (46/300 sampled have internal_team label)",
  "community_stale_pct": "~29% (88/300 sampled have inactive label)",

  "recommendations": [
    "Close #15409 — OAuth fix is already shipped in v1.9.11",
    "Escalate #15316 (agents.db backup corruption) — active data integrity issue in milestone v1.9.8",
    "Triage #15826 (@cherrystudio/ai-core CJS exports) — affects external package consumers",
    "Review 102 inactive-labeled open issues — many could be closed",
    "Add P1/severity labels to #15316 and #15826 to make triage easier"
  ]
}
